[1,["dc6EXKZqdE3bGMvUmHbhqa","834FFm1hFFKqwvTL9cPVoG","b8OSNRvpdPAZhePn0hGPPJ","7cy3hPfFFKC6We6V2kDzAT","16uyqzQSZNj7KqgKIWBIv6"],["node","_textureSetter","root","scene","_parent","asset","_spriteFrame","_defaultClip"],[["cc.Node",["_name","_zIndex","_id","_trs","_components","_parent","_contentSize","_children","_prefab"],0,7,9,1,5,2,4],"cc.SpriteFrame",["cc.SceneAsset",["_name","asyncLoadAssets"],1],["cc.Node",["_name","_zIndex","_parent","_components","_contentSize","_trs"],1,1,12,5,7],["cc.Canvas",["node"],3,1],["cc.Widget",["_alignFlags","node"],2,1],["cc.Scene",["_name","_zIndex","autoReleaseAssets","_children","_contentSize","_trs"],0,2,5,7],["cc.Sprite",["node","_spriteFrame"],3,1,6],["cc.Camera",["_clearFlags","_depth","node"],1,1],["cc.PrefabInfo",["fileId","sync","root","asset"],1,1,6],["cc.Animation",["playOnLoad","node","_clips"],2,1,3],["e4f88adp3hERoJ48DZ2PSAl",["_srcBlendFactor","_string","_N$horizontalAlign","_N$verticalAlign","_N$textKey","node"],-2,1],["ae6fcR8cuFGRYHW525VJD/k",["node","sheepAnim"],3,1,1],["6a871gy73FDLap3Eje/2h6i",["text","node"],2,1]],[[0,0,1,2,5,4,3,4],[2,0,1,3],[0,0,1,2,7,4,6,3,4],[0,0,1,5,4,3,3],[0,0,5,8,3,2],[0,0,1,5,4,6,3,3],[3,0,1,2,3,4,5,3],[4,0,1],[5,0,1,2],[6,0,1,2,3,4,5,4],[7,0,1,1],[8,0,1,2,3],[9,0,1,2,3,3],[10,0,1,2,2],[11,0,1,2,3,4,5,6],[12,0,1,1],[13,0,1,2]],[[[{"name":"sheep_run_0","rect":[178,236,168,113],"offset":[-4,0],"originalSize":[228,159],"capInsets":[0,0,0,0]}],[1],0,[0],[1],[1]],[[[1,"SpriteAnimation",null],[2,"Canvas",0,"14c4azE7yxPz6NM7YE0OAbb",[-3,-4,-5,-6],[[7,-1],[8,45,-2]],[5,960,640],[480,320,0,0,0,0,0,1,1,1]],[9,"New Node",0,true,[1,-7,-8],[5,100,100],[0,0,0,0,0,0,1,0.5697916666666667,0.5697916666666667,1]],[6,"Sheep",0,1,[[[10,-9,1],-10],4,1],[5,168,113],[0,0,0,0,0,0,0,1,1,1]],[3,"Main Camera",0,1,[[11,7,-1,-11]],[0,0,0,0,0,0,0,1,1,1]],[4,"Background",1,[12,"78fd70+ls5GgJcFkzvLSRk8",true,-12,0],[0,0,0,0,0,0,0,1,1,1]],[13,true,3,[2,3]],[5,"Tips",0,1,[[14,1,"这是精灵帧动画",1,1,"cases/03_gameplay/03_animation/SpriteAnimation.fire.9",-13]],[5,280,40],[0,-207,0,0,0,0,0,1,1,1]],[0,"SheepAnimationCtrl",0,"e7287lZKuBCyoyoWdifRdWD",2,[[15,-14,6]],[0,0,0,0,0,0,0,1,1,1]],[0,"Instruction",0,"a8ba7qJtIFJhp/csDPhAYB6",2,[[16,"## Sprite Animation 基本用法\n\n1. 打开 Timeline 面板（Main-Menu/Panel/Timeline）\n2. 选中 sheep 节点，应该可以看到 Timeline 中显示了 cc.Sprite.sprite 轨道和动画帧\n3. [Timeline面板]点击播放按钮，可以预览动画播放；在刻度区域点击鼠标，可以操作动画指针显示指定关键帧位置的图像\n4. [Timeline面板]点击 clip 下拉菜单，可以从 sheep_run 和 sheep_jump 中选择，并可以用上述方法预览\n5. 点击编辑器的预览按钮，在浏览器中打开场景，游戏启动后会先循环播放 sheep_run，2秒钟后播放 sheep_jump\n6. 查看 Sheep_Animation_1.js 文件，了解 cc.AnimationComponent.play() 接口的用法。\n\n\n## Sprite Animation 创建工作流程（后续会大幅简化）\n\n1. 新建一个节点，为其添加 Sprite 和 AnimationComponent 组件\n2. 在 Asset 面板新建一个 AnimationClip，并妥善命名\n3. 选中刚才的节点，在 AnimationComponent 组件里把 Animations 列表的容量设为 1 或更多\n4. 将刚才新建的 AnimationClip 拖入 AnimationComponent.Animations 列表中\n5. 打开 Timeline 面板，在选中刚才新建节点的情况下，确认 clip 下拉菜单里已经选中刚创建的 AnimationClip\n6. [Timeline] 在 property 列表中点击 Add Property 按钮，选择添加 cc.Sprite.sprite 属性轨道\n7. 从 Asset 面板中拖拽你希望在动画中显示的 Sprite 资源到 cc.Sprite.sprite 轨道，拖拽时可以指定添加该关键帧的时间轴位置。\n8. [Timeline] 点击播放按钮预览帧动画",-15]],[0,0,0,0,0,0,0,1,1,1]]],0,[0,0,1,0,0,1,0,-1,4,0,-2,5,0,-3,3,0,-4,7,0,-2,8,0,-3,9,0,0,3,0,-2,6,0,0,4,0,2,5,0,0,7,0,0,8,0,0,9,0,3,2,1,4,2,15],[0,0,0,0,6],[5,6,-1,-2,7],[2,3,0,4,0]]]]